UGFlib/__init__.py
UGFlib/ROOT/__init__.py
UGFlib/RooFit/__init__.py
UGFlib-0.0.1.dist-info/LICENSE
UGFlib-0.0.1.dist-info/METADATA
UGFlib-0.0.1.dist-info/WHEEL
UGFlib-0.0.1.dist-info/top_level.txt
UGFlib-0.0.1.dist-info/RECORD
